pyffish_alice.cpython-38-darwin.so
pyffish_alice-0.0.2.dist-info/RECORD
pyffish_alice-0.0.2.dist-info/AUTHORS
pyffish_alice-0.0.2.dist-info/WHEEL
pyffish_alice-0.0.2.dist-info/top_level.txt
pyffish_alice-0.0.2.dist-info/METADATA
