Metadata-Version: 2.1
Name: pyffish_alice
Version: 0.0.2
Summary: Fairy-Stockfish alice branch Python wrapper
Home-page: https://github.com/gbtami/Fairy-Stockfish
Author: Bajusz Tamás
Author-email: gbtami@gmail.com
License: GPL3
Classifier: Development Status :: 3 - Alpha
Classifier: License :: OSI Approved :: GNU General Public License v3 (GPLv3)
Classifier: Programming Language :: Python :: 3
Classifier: Operating System :: OS Independent
Requires-Python: >=2.7,!=3.0.*,!=3.1.*,!=3.2.*,!=3.3.*
License-File: Copying.txt
License-File: AUTHORS
